[
  {
    "_id": "MhBWuy8Aw6mJTy855",
    "name": "Arfiya",
    "surname": "Naseem",
    "professionaltitles": ["Psychologist (Counselling)"],
    "terms": true,
    "isorganisation": false,
    "newUser": true,
    "availabilityStatus": "available",
    "nextAvailabilityEmailDate": "2022-06-12T07:38:43.430Z",
    "firstAvailabilityEmailDate": "2022-05-15T07:38:43.431Z",
    "firstAvailabilityEmail": true,
    "logoImage": false,
    "sliderStats": 24,
    "emailStats": 3,
    "suggestStats": 0,
    "minisiteStats": 19,
    "calendarClick": 0,
    "showNumberStats": 0,
    "emailOnNumberClick": true,
    "hide5": true,
    "hidePhone": false,
    "layout": "one-page",
    "colour": "1",
    "hideSitePhoneNumber": true,
    "isVerified": false,
    "boostUser": false,
    "approved": true,
    "hideprofile": false,
    "receiveemails": false,
    "agegroups": [
      "All ages",
      "Adolescents",
      "Adults",
      "Couples",
      "Families",
      "Individuals"
    ],
    "distanceTherapy": true,
    "fees": "Please inquire",
    "gender": ["Female"],
    "languages": ["English", "Hindi/Urdu"],
    "licenses": [
      {
        "organisation": "Amity University"
      }
    ],
    "offices": [
      {
        "title": "Naseem's",
        "country": "India",
        "address1": "Mutakkipur, Sitapur bypass",
        "suburb": "Lucknow",
        "city": "Lucknow",
        "postcode": "226003",
        "province": "Uttar pradesh",
        "officenumber": "9536756112"
      }
    ],
    "professionalname": "M.A Clinical Pyschology",
    "publicprivate": "private",
    "qualifications": [
      {
        "degrees": "M. A Clinical Psychology",
        "institution": "Amity University",
        "yearcompletion": 2021
      }
    ],
    "scope": [
      "Anxiety Disorders",
      "Depression",
      "Family Problems",
      "Mood Swings / Mood Disturbance",
      "Self-Love",
      "Stress Management"
    ],
    "services": [
      "Awareness",
      "Counselling (General)",
      "Psychoanalysis",
      "Psychoeducation",
      "Psychology (Counselling)",
      "Psychotherapy (CBT)",
      "Stress Management",
      "Therapy (Online)",
      "Wellness"
    ],
    "someinfo": "A competent and compassionate counseling psychologist who uses eclectic approach which mostly involves CBT and humanistic or client centered approach to facilitate people of all ages with their mental health concerns.",
    "title": "Miss",
    "geopoint": [80.9348382, 26.9309771],
    "latitude": "26.9309771",
    "loca": {
      "type": "MultiPoint",
      "coordinates": [[80.9348382, 26.9309771]]
    },
    "longitude": "80.9348382",
    "searchcity": "Lucknow",
    "searchcountry": "India",
    "searchprovince": "Uttar pradesh",
    "searchsuburb": "Lucknow",
    "bodyfont": "Lato",
    "customBlogTitle": "Blog",
    "fontcolour": "#FFF",
    "headingfont": "Slabo",
    "hide3": true,
    "publishSite": true,
    "siteurl": "arfiya-naseem-lucknow-india",
    "splashimage": "https://res.cloudinary.com/dywkbcfp5/image/upload/f_auto/v1542969244/fecevh41fgihtkrnop17.png",
    "userimageCloudinary": {
      "api_key": "139845823459914",
      "asset_id": "a80c0ccde177b320a8f3fee59e6e4831",
      "bytes": 186373,
      "created_at": "2022-05-15T11:06:13Z",
      "etag": "cc77a654995d240ce9be242fd3a80c8e",
      "format": "jpg",
      "height": 845,
      "original_filename": "20201212_214949",
      "placeholder": false,
      "public_id": "qfcikigm9ngzdmixmg5j",
      "resource_type": "image",
      "secure_url": "https://res.cloudinary.com/dywkbcfp5/image/upload/v1652612773/qfcikigm9ngzdmixmg5j.jpg",
      "signature": "a1ef93b0ab63d64c1d38068dae0ba97032c866c1",
      "type": "upload",
      "url": "http://res.cloudinary.com/dywkbcfp5/image/upload/v1652612773/qfcikigm9ngzdmixmg5j.jpg",
      "version": 1652612773,
      "version_id": "695560d4101e23bad19014fe82ad45ee",
      "width": 682
    },
    "userimage": "https://res.cloudinary.com/dywkbcfp5/image/upload/v1652612773/qfcikigm9ngzdmixmg5j.jpg",
    "officeNumber": "9536756112"
  },
  {
    "_id": "yyk9jydyYM8aSCh22",
    "name": "Deepak",
    "surname": "Bhatia",
    "professionaltitles": ["Psychologist (Counselling)"],
    "terms": true,
    "isorganisation": false,
    "logoImage": false,
    "sliderStats": 1676,
    "emailStats": 5,
    "suggestStats": 36,
    "minisiteStats": 262,
    "showNumberStats": 75,
    "emailOnNumberClick": true,
    "hide5": true,
    "hidePhone": false,
    "layout": "one-page",
    "colour": "1",
    "hideSitePhoneNumber": true,
    "isVerified": false,
    "approved": true,
    "hideprofile": false,
    "receiveemails": false,
    "agegroups": [
      "Adolescents",
      "Adults",
      "Children",
      "Couples",
      "Elderly",
      "Families",
      "Individuals",
      "Organisations",
      "Parents"
    ],
    "distanceTherapy": true,
    "fees": "Please inquire",
    "gender": ["Asian"],
    "languages": ["English", "Hindi/Urdu", "Punjabi"],
    "licenses": [
      {
        "organisation": "LMBCPA",
        "category": "Counselling Psychologist",
        "region": "INDIA"
      }
    ],
    "offices": [
      {
        "title": "Consultant Counselling Psychologist",
        "country": "India",
        "address1": "Lucknow",
        "suburb": "Lucknow",
        "city": "Lucknow",
        "postcode": "226012",
        "province": "Uttar Pradesh",
        "officenumber": "91-9415741509"
      }
    ],
    "professionalname": "Counselling Psychologist",
    "professionaltitlecustom": "Counsellor",
    "publicprivate": "private",
    "qualifications": [
      {
        "degrees": "PG COUNSELLING PSYCHOLOGY, CIG",
        "institution": "IGNOU",
        "yearcompletion": 2018
      }
    ],
    "scope": [
      "Adjusting to Change/Life Transitions",
      "Behavioural and Emotional Problems",
      "Career Issues",
      "Grandparenting Issues",
      "Life Balance",
      "Online Counselling",
      "Parenting Issues",
      "Performance Enhancement",
      "School/Work Adjustment",
      "Workplace Issues"
    ],
    "services": [
      "Coaching (Business)",
      "Consultation",
      "Counselling",
      "Counselling (Career)",
      "Psychology (Educational)",
      "Training (Life Skills)",
      "Wellness"
    ],
    "someinfo": "Deepak Bhatia is Consultant Counselling Psychologist having Masters Degree in Counselling Psychology, Masters in Human Resource Management",
    "title": "Mr",
    "userimageCloudinary": {
      "asset_id": "2ba47d79613f489da7ee5446ca8cf189",
      "bytes": 29980,
      "created_at": "2021-01-31T19:03:45Z",
      "etag": "ba840aad63ea82aad1b3d55cd4a07cb2",
      "format": "jpg",
      "height": 395,
      "original_filename": "DEEPAK BHATIA AB",
      "placeholder": false,
      "public_id": "omikwt084dpytxsyheas",
      "resource_type": "image",
      "secure_url": "https://res.cloudinary.com/dywkbcfp5/image/upload/v1612119825/omikwt084dpytxsyheas.jpg",
      "signature": "62ec217e3ad854d35d76e5b45e8d10e40ffd1e38",
      "type": "upload",
      "url": "http://res.cloudinary.com/dywkbcfp5/image/upload/v1612119825/omikwt084dpytxsyheas.jpg",
      "version": 1612119825,
      "version_id": "f111326fb06373bea36f8f3cfc1e8264",
      "width": 335
    },
    "userimage": "https://res.cloudinary.com/dywkbcfp5/image/upload/v1612119825/omikwt084dpytxsyheas.jpg",
    "geopoint": [80.9152434, 26.7814955],
    "latitude": "26.7814955",
    "loca": {
      "type": "MultiPoint",
      "coordinates": [[80.9152434, 26.7814955]]
    },
    "longitude": "80.9152434",
    "searchcity": "Lucknow",
    "searchcountry": "India",
    "searchprovince": "Uttar Pradesh",
    "searchsuburb": "Lucknow",
    "bodyfont": "Lato",
    "customBlogTitle": "Blog",
    "fontcolour": "#FFF",
    "headingfont": "Slabo",
    "hide3": true,
    "publishSite": true,
    "siteurl": "deepak-bhatia-lucknow-in",
    "splashimage": "https://res.cloudinary.com/dywkbcfp5/image/upload/f_auto/v1542969244/fecevh41fgihtkrnop17.png",
    "showregnumber": false,
    "boostUser": false,
    "firstAvailabilityEmail": true,
    "firstAvailabilityEmailDate": "2022-05-03T06:18:36.894Z",
    "availabilityStatus": "available",
    "nextAvailabilityEmailDate": "2022-05-31T06:18:36.894Z",
    "officeNumber": "91-9415741509"
  },
  {
    "_id": "d4FXtM2aqfzg3NzeY",
    "name": "Health of Minds",
    "organisationtype": ["Counselling Centre"],
    "terms": true,
    "isorganisation": true,
    "logoImage": true,
    "sliderStats": 176,
    "emailStats": 0,
    "suggestStats": 3,
    "minisiteStats": 50,
    "calendarClick": 0,
    "showNumberStats": 11,
    "emailOnNumberClick": true,
    "hide5": true,
    "hidePhone": false,
    "layout": "one-page",
    "colour": "1",
    "hideSitePhoneNumber": true,
    "isVerified": false,
    "boostUser": false,
    "approved": true,
    "hideprofile": false,
    "receiveemails": false,
    "agegroups": ["Adults", "Couples", "Individuals", "Parents"],
    "fees": "Direct payment",
    "languages": ["English", "Hindi/Urdu"],
    "licenses": [
      {
        "organisation": "Lucknow University"
      }
    ],
    "offices": [
      {
        "title": "Health of Minds",
        "country": "India",
        "address1": "Butler Colony",
        "address2": "Near Fortune Park BBD",
        "suburb": "Lucknow",
        "city": "Lucknow",
        "postcode": "226001",
        "province": "Uttar Pradesh",
        "officenumber": "+91 7376032562"
      }
    ],
    "publicprivate": "private",
    "servicesorg": [
      "Counselling (General)",
      "Counselling (Trauma)",
      "Psychology (Counselling)",
      "Psychotherapy",
      "Psychotherapy (CBT)",
      "Therapy (Individual)",
      "Therapy (Online)"
    ],
    "servicesorgcustom": "Mental health and wellness",
    "someinfo": "Private practice run by a group of passionate mental health professionals who work with their clients with all their zeal.\nHealth of Minds started as a passion project by our founder to offer affordable counselling/psychotherapy sessions to everyone (fees per session is under 1000 rupees)",
    "staff": [
      "CBT Psychotherapists",
      "Psychologists (Counselling)",
      "Therapists/Counsellors Practicing Under Supervision"
    ],
    "userimageCloudinary": {
      "api_key": "139845823459914",
      "asset_id": "3f0567f3420859595d7592ccf75a01a2",
      "bytes": 16269,
      "created_at": "2021-12-07T05:50:13Z",
      "etag": "942bf91c787de4ad6ef7d5e7bd32801c",
      "format": "png",
      "height": 500,
      "original_filename": "[Original size] HOM logo",
      "placeholder": false,
      "public_id": "qfy8lqbpmu96lsavrrii",
      "resource_type": "image",
      "secure_url": "https://res.cloudinary.com/dywkbcfp5/image/upload/v1638856213/qfy8lqbpmu96lsavrrii.png",
      "signature": "1212dfc602dfc432202fd851985dc793518ca51b",
      "type": "upload",
      "url": "http://res.cloudinary.com/dywkbcfp5/image/upload/v1638856213/qfy8lqbpmu96lsavrrii.png",
      "version": 1638856213,
      "version_id": "422e5d59c197e71a4530c2cd252ad719",
      "width": 500
    },
    "userimage": "https://res.cloudinary.com/dywkbcfp5/image/upload/v1638856213/qfy8lqbpmu96lsavrrii.png",
    "geopoint": [80.9577743, 26.8550095],
    "latitude": "26.8550095",
    "loca": {
      "type": "MultiPoint",
      "coordinates": [[80.9577743, 26.8550095]]
    },
    "longitude": "80.9577743",
    "searchcity": "Lucknow",
    "searchcountry": "India",
    "searchprovince": "Uttar Pradesh",
    "searchsuburb": "Lucknow",
    "bodyfont": "Lato",
    "customBlogTitle": "Blog",
    "fontcolour": "#FFF",
    "headingfont": "Slabo",
    "hide3": true,
    "publishSite": true,
    "siteurl": "health-of-minds-lucknow-india",
    "splashimage": "https://res.cloudinary.com/dywkbcfp5/image/upload/f_auto/v1542969244/fecevh41fgihtkrnop17.png",
    "firstAvailabilityEmail": true,
    "firstAvailabilityEmailDate": "2022-04-30T01:00:29.645Z",
    "officeNumber": "+91 7376032562"
  },
  {
    "_id": "gi2JFPgjQ2e6vgQFN",
    "name": "Ishangi",
    "surname": "Mishra",
    "professionaltitles": ["Psychologist (Counselling)"],
    "terms": true,
    "isorganisation": false,
    "logoImage": false,
    "sliderStats": 1133,
    "emailStats": 1,
    "suggestStats": 7,
    "minisiteStats": 316,
    "showNumberStats": 81,
    "emailOnNumberClick": true,
    "hide5": true,
    "hidePhone": false,
    "layout": "one-page",
    "colour": "1",
    "hideSitePhoneNumber": true,
    "isVerified": false,
    "approved": true,
    "hideprofile": false,
    "receiveemails": false,
    "seenPhoneNumber": ["f3RnZ6xMMhYmxD2k7"],
    "agegroups": ["All ages"],
    "distanceTherapy": true,
    "fees": "Please inquire",
    "gender": ["Asian"],
    "languages": ["English", "Hindi/Urdu"],
    "licenses": [
      {
        "organisation": "Counsellors council of India",
        "regnumber": "CRN5414339"
      }
    ],
    "offices": [
      {
        "title": "Online",
        "country": "India",
        "address1": "Online Service",
        "suburb": "India",
        "city": "Lucknow",
        "postcode": "226024",
        "province": "Uttar Pradesh",
        "officenumber": "Email only"
      }
    ],
    "professionalname": "Msc clinical psychology",
    "publicprivate": "private",
    "qualifications": [
      {
        "degrees": "Msc psychology specialisation in clinical psychology",
        "institution": "Jain deemed to be university",
        "yearcompletion": 2020
      }
    ],
    "scope": [
      "Adolescent Counselling",
      "Behavioural and Emotional Problems",
      "Career Issues",
      "Mental Health",
      "Pre-Marital Counselling",
      "Relationship Counselling",
      "Workplace Issues",
      "Young Adult Issues"
    ],
    "services": ["Art Therapy", "Counselling", "Psychoeducation", "Therapy"],
    "someinfo": "An experienced psychologist with a demonstrated history of working with kids and adults. Skilled in counselling and behavioural management.",
    "title": "Miss",
    "userimage": "https://res.cloudinary.com/dywkbcfp5/image/upload/v1629716244/lhfhaw7uilbkbe4sbxga.jpg",
    "geopoint": [80.95250399999999, 26.883215],
    "latitude": "26.883215",
    "loca": {
      "type": "MultiPoint",
      "coordinates": [[80.95250399999999, 26.883215]]
    },
    "longitude": "80.95250399999999",
    "searchcity": "Lucknow",
    "searchcountry": "India",
    "searchprovince": "Uttar Pradesh",
    "searchsuburb": "India",
    "bodyfont": "Lato",
    "customBlogTitle": "Blog",
    "fontcolour": "#FFF",
    "headingfont": "Slabo",
    "hide3": true,
    "publishSite": true,
    "siteurl": "ishangi-mishra-lucknowbangalore-india",
    "splashimage": "https://res.cloudinary.com/dywkbcfp5/image/upload/f_auto/v1542969244/fecevh41fgihtkrnop17.png",
    "showregnumber": false,
    "hidecontact": true,
    "hidecontactform": true,
    "backgroundimage": "0",
    "boostUser": false,
    "firstAvailabilityEmail": true,
    "firstAvailabilityEmailDate": "2022-04-30T05:00:12.083Z",
    "availabilityStatus": null,
    "nextAvailabilityEmailDate": null,
    "officeNumber": "Email only"
  },
  {
    "_id": "36YDdckmrmed6LyqW",
    "name": "VIikas Singh",
    "surname": "Rawat",
    "professionaltitles": ["Psychologist (Clinical)"],
    "terms": true,
    "isorganisation": false,
    "logoImage": false,
    "sliderStats": 897,
    "emailStats": 0,
    "suggestStats": 10,
    "minisiteStats": 93,
    "showNumberStats": 13,
    "emailOnNumberClick": true,
    "hide5": true,
    "hidePhone": false,
    "layout": "one-page",
    "colour": "1",
    "hideSitePhoneNumber": true,
    "isVerified": false,
    "approved": true,
    "hideprofile": false,
    "receiveemails": false,
    "agegroups": [
      "Adolescents",
      "Children",
      "Couples",
      "Families",
      "Individuals"
    ],
    "distanceTherapy": true,
    "fees": "Please inquire",
    "languages": ["English", "Hindi/Urdu"],
    "licenses": [
      {
        "organisation": "REHABILITATION COUNCIL OF INDIA",
        "category": "CLINICAL PSYCHOLOGIST"
      }
    ],
    "offices": [
      {
        "title": "Online from...",
        "country": "India",
        "address1": "Lucknow",
        "suburb": "Lucknow",
        "city": "Lucknow",
        "postcode": "226003",
        "province": "Uttar Pradesh",
        "officenumber": "9354704478"
      }
    ],
    "professionalname": "BRT, M.A, MPhil. Clinical Psychology",
    "publicprivate": "private",
    "qualifications": [
      {
        "degrees": "MPHIL. CLINICAL PSYCHOLOGY",
        "institution": "PGIBAMS",
        "yearcompletion": 2017
      }
    ],
    "scope": [
      "Child Stress and Trauma",
      "Disability (Intellectual)",
      "Family Problems"
    ],
    "services": [
      "Assessment (Children)",
      "Counselling (Family)",
      "Treatment (Therapeutic)"
    ],
    "someinfo": "BEST CLINICAL PSYCHOLOGIST",
    "title": "Mr",
    "userimageCloudinary": {
      "api_key": "139845823459914",
      "asset_id": "28b2e82efbee6d09099a68c42d843614",
      "bytes": 63545,
      "created_at": "2021-08-02T17:11:28Z",
      "etag": "18492638ec496a769b885b47ee749182",
      "format": "jpg",
      "height": 672,
      "original_filename": "Untitled-1 (3)",
      "placeholder": false,
      "public_id": "xwxam7wrstawcxauekxo",
      "resource_type": "image",
      "secure_url": "https://res.cloudinary.com/dywkbcfp5/image/upload/v1627924288/xwxam7wrstawcxauekxo.jpg",
      "signature": "399b75e5cd045841674323146c928af626935f85",
      "type": "upload",
      "url": "http://res.cloudinary.com/dywkbcfp5/image/upload/v1627924288/xwxam7wrstawcxauekxo.jpg",
      "version": 1627924288,
      "version_id": "6dffd78a488dd20ae659ea9ddab87b2f",
      "width": 481
    },
    "userimage": "https://res.cloudinary.com/dywkbcfp5/image/upload/v1627924288/xwxam7wrstawcxauekxo.jpg",
    "geopoint": [80.8820535, 26.872781],
    "latitude": "26.872781",
    "loca": {
      "type": "MultiPoint",
      "coordinates": [[80.8820535, 26.872781]]
    },
    "longitude": "80.8820535",
    "searchcity": "Lucknow",
    "searchcountry": "India",
    "searchprovince": "Uttar Pradesh",
    "searchsuburb": "Lucknow",
    "bodyfont": "Lato",
    "customBlogTitle": "Blog",
    "fontcolour": "#FFF",
    "headingfont": "Slabo",
    "hide3": true,
    "publishSite": true,
    "siteurl": "vikas-singh-rawat-lucknow-india",
    "splashimage": "https://res.cloudinary.com/dywkbcfp5/image/upload/f_auto/v1542969244/fecevh41fgihtkrnop17.png",
    "showregnumber": false,
    "boostUser": false,
    "firstAvailabilityEmail": true,
    "firstAvailabilityEmailDate": "2022-05-08T08:00:01.301Z",
    "availabilityStatus": null,
    "nextAvailabilityEmailDate": null,
    "officeNumber": "9354704478"
  },
  {
    "_id": "D5kuHvCDfRbfSZ4f2",
    "name": "Hansita",
    "surname": "Yadav",
    "professionaltitles": ["Psychologist (Clinical)"],
    "terms": true,
    "isorganisation": false,
    "logoImage": false,
    "sliderStats": 786,
    "emailStats": 6,
    "suggestStats": 24,
    "minisiteStats": 209,
    "showNumberStats": 89,
    "emailOnNumberClick": true,
    "hide5": true,
    "hidePhone": false,
    "layout": "one-page",
    "colour": "1",
    "hideSitePhoneNumber": true,
    "isVerified": false,
    "approved": true,
    "hideprofile": false,
    "receiveemails": false,
    "agegroups": [
      "Adolescents",
      "Adults",
      "Couples",
      "Elderly",
      "Families",
      "Individuals"
    ],
    "distanceTherapy": true,
    "fees": "Subsidised service",
    "gender": ["Female"],
    "languages": ["English", "Hindi/Urdu"],
    "licenses": [
      {
        "organisation": "Psychologist (clinical)"
      }
    ],
    "offices": [
      {
        "title": "HOPE",
        "country": "India",
        "address1": "Ashiyana lucknow",
        "suburb": "Lucknow",
        "city": "Lucknow",
        "postcode": "226002",
        "province": "Lucknow",
        "officenumber": "8115995717"
      }
    ],
    "professionalname": "M.A. Applied Clin Psych",
    "publicprivate": "private",
    "qualifications": [
      {
        "degrees": "M.A. Applied clinical psychology",
        "institution": "TATA institute of social sciences",
        "yearcompletion": 2019
      }
    ],
    "scope": [
      "Adjusting to Change/Life Transitions",
      "Adolescent Counselling",
      "Attention Deficit Disorders",
      "Behavioural and Emotional Problems",
      "Child and/or Adolescent Issues",
      "Depression",
      "Family Problems",
      "Online Counselling",
      "Personal Growth"
    ],
    "services": [
      "Coaching (Life)",
      "Counselling (General)",
      "Emotional Intelligence",
      "Individual and Couple Therapy",
      "Online Counselling / Phone Therapy",
      "Psychoeducation",
      "Psychotherapy",
      "Training (Life Skills)"
    ],
    "someinfo": "A psychologist (clinical) who is trained to aid the wellbeing of people with mental health issues through psychosocial interventions, therapy and counselling.",
    "title": "Miss",
    "userimageCloudinary": {
      "api_key": "139845823459914",
      "asset_id": "e9956830055083225914ccd6d0f16aa6",
      "bytes": 307646,
      "created_at": "2021-06-26T18:53:57Z",
      "etag": "cb5a2726a2426472c4c4abe7c2cd5db9",
      "format": "jpg",
      "height": 1624,
      "original_filename": "t3bbtveibdg7ooatadx3",
      "placeholder": false,
      "public_id": "waxi0zrjsclxivfrpikx",
      "resource_type": "image",
      "secure_url": "https://res.cloudinary.com/dywkbcfp5/image/upload/v1624733637/waxi0zrjsclxivfrpikx.jpg",
      "signature": "05165c8ab04f302226e38044e2fe772fcb483f88",
      "type": "upload",
      "url": "http://res.cloudinary.com/dywkbcfp5/image/upload/v1624733637/waxi0zrjsclxivfrpikx.jpg",
      "version": 1624733637,
      "version_id": "dd744d235135c503414f6f75fd96f300",
      "width": 1080
    },
    "userimage": "https://res.cloudinary.com/dywkbcfp5/image/upload/v1624733637/waxi0zrjsclxivfrpikx.jpg",
    "geopoint": [80.9191096, 26.7837459],
    "latitude": "26.7837459",
    "loca": {
      "type": "MultiPoint",
      "coordinates": [[80.9191096, 26.7837459]]
    },
    "longitude": "80.9191096",
    "searchcity": "Lucknow",
    "searchcountry": "India",
    "searchprovince": "Lucknow",
    "searchsuburb": "Lucknow",
    "bodyfont": "Lato",
    "customBlogTitle": "Blog",
    "fontcolour": "#FFF",
    "headingfont": "Slabo",
    "hide3": true,
    "publishSite": true,
    "siteurl": "hansita-yadav-lucknow-in",
    "splashimage": "https://res.cloudinary.com/dywkbcfp5/image/upload/f_auto/v1542969244/fecevh41fgihtkrnop17.png",
    "showregnumber": false,
    "boostUser": false,
    "firstAvailabilityEmail": true,
    "firstAvailabilityEmailDate": "2022-04-30T01:00:27.990Z",
    "officeNumber": "8115995717"
  },
  {
    "_id": "ESSQqcCWX7JzJ9DRx",
    "name": "Tanya",
    "surname": "Dixit",
    "professionaltitles": ["Psychologist (Counselling)"],
    "terms": true,
    "isorganisation": false,
    "logoImage": false,
    "sliderStats": 1605,
    "emailStats": 17,
    "suggestStats": 13,
    "minisiteStats": 575,
    "showNumberStats": 211,
    "emailOnNumberClick": true,
    "hide5": true,
    "hidePhone": false,
    "layout": "one-page",
    "colour": "1",
    "hideSitePhoneNumber": true,
    "isVerified": false,
    "approved": true,
    "hideprofile": false,
    "receiveemails": false,
    "agegroups": [
      "Adolescents",
      "Children",
      "Families",
      "Groups",
      "Individuals",
      "Parents"
    ],
    "distanceTherapy": true,
    "fees": "Direct payment",
    "gender": ["Female"],
    "licenses": [
      {
        "organisation": "CCI, BCPA, APA",
        "category": "Counseling Professional",
        "region": "UTTAR PRADESH",
        "regnumber": "CRN289666"
      }
    ],
    "offices": [
      {
        "title": "Shubhkamna Counselling and Life-skills Training Centre",
        "country": "India",
        "address1": "242/133, Yahiyaganj, Lucknow",
        "suburb": "Lucknow",
        "city": "Lucknow",
        "postcode": "226003",
        "province": "UTTAR PRADESH",
        "officenumber": "91-8924802565",
        "officeextension": "91-8924802565",
        "officefax": "91-8924802565"
      }
    ],
    "professionalname": "MA. PhD. , Counseling Psychologist",
    "publicprivate": "private",
    "qualifications": [
      {
        "degrees": "MA. PhD.",
        "institution": "University of Lucknow",
        "yearcompletion": 2020
      }
    ],
    "scope": [
      "Adolescent Counselling",
      "Anger Management Issues",
      "Anxiety Disorders",
      "Child and/or Adolescent Issues",
      "Depression",
      "Online Counselling",
      "Parenting Issues",
      "Relationship Counselling",
      "Stress Management",
      "Telephone Counselling"
    ],
    "services": [
      "Assessment (Personality)",
      "Assessment (Psychometric)",
      "Child and Adolescent Services",
      "Counselling (Career)",
      "Counselling (Parent)",
      "Psychology (Counselling)",
      "Relationship Counselling",
      "Training (Assertiveness)",
      "Training (Communication Skills)",
      "Training (Life Skills)"
    ],
    "someinfo": "My mission is to BRING SMILE ON SAD FACES AND SPREAD POSITIVITY IN WORLD. I like to cater my services for the welfare of humanity.",
    "title": "Dr",
    "userimageCloudinary": {
      "asset_id": "975b10c8245d9d241daf456484bbb7fc",
      "bytes": 1671365,
      "created_at": "2021-05-18T04:49:09Z",
      "etag": "40917e3b30edd0c890ff025396893785",
      "format": "jpg",
      "height": 5184,
      "original_filename": "IMG_20200806_152724",
      "placeholder": false,
      "public_id": "qtpe3naa9f1ej2ejj8ai",
      "resource_type": "image",
      "secure_url": "https://res.cloudinary.com/dywkbcfp5/image/upload/v1621313349/qtpe3naa9f1ej2ejj8ai.jpg",
      "signature": "0812964b48b507422ef36d21bd78b1ebaf4e8b38",
      "type": "upload",
      "url": "http://res.cloudinary.com/dywkbcfp5/image/upload/v1621313349/qtpe3naa9f1ej2ejj8ai.jpg",
      "version": 1621313349,
      "version_id": "1630832dee0e61d43b40abbee4d395c1",
      "width": 3880
    },
    "userimage": "https://res.cloudinary.com/dywkbcfp5/image/upload/v1621313349/qtpe3naa9f1ej2ejj8ai.jpg",
    "geopoint": [80.910791, 26.8563327],
    "latitude": "26.8563327",
    "loca": {
      "type": "MultiPoint",
      "coordinates": [[80.910791, 26.8563327]]
    },
    "longitude": "80.910791",
    "searchcity": "Lucknow",
    "searchcountry": "India",
    "searchprovince": "UTTAR PRADESH",
    "searchsuburb": "Lucknow",
    "bodyfont": "Lato",
    "customBlogTitle": "Blog",
    "fontcolour": "#FFF",
    "headingfont": "Slabo",
    "hide3": true,
    "publishSite": true,
    "siteurl": "dr-tanya-dixit-lucknow-in",
    "splashimage": "https://res.cloudinary.com/dywkbcfp5/image/upload/f_auto/v1542969244/fecevh41fgihtkrnop17.png",
    "showregnumber": false,
    "boostUser": false,
    "firstAvailabilityEmail": true,
    "firstAvailabilityEmailDate": "2022-04-30T06:00:15.137Z",
    "availabilityStatus": null,
    "nextAvailabilityEmailDate": null,
    "officeNumber": "91-8924802565"
  },
  {
    "_id": "X3TYJbasBKmfMSAJG",
    "name": "Dr. Nitnem Singh Sodhi (neuro-psychologist) | Modern Healing Centre",
    "organisationtype": ["Mental Health Clinic"],
    "terms": true,
    "isorganisation": true,
    "logoImage": false,
    "sliderStats": 311,
    "emailStats": 13,
    "suggestStats": 5,
    "minisiteStats": 446,
    "showNumberStats": 94,
    "emailOnNumberClick": true,
    "hide5": true,
    "hidePhone": false,
    "layout": "one-page",
    "colour": "1",
    "hideSitePhoneNumber": true,
    "isVerified": false,
    "approved": true,
    "hideprofile": false,
    "receiveemails": false,
    "agegroups": ["All ages"],
    "fees": "Direct payment",
    "licenses": [
      {
        "organisation": "Professional : Neuro-Psychologist, International Research Scientist"
      }
    ],
    "offices": [
      {
        "title": "Modern Healing Centre",
        "country": "India",
        "address1": "First Floor, Apna Bazar, Vrindavan Yojna",
        "address2": "Behind Allen House Public School, Near Telibagh Chauraha",
        "suburb": "Lucknow",
        "city": "Lucknow",
        "postcode": "226012",
        "province": "Uttar Pradesh",
        "officenumber": "+91 9235344444"
      }
    ],
    "publicprivate": "public",
    "servicesorg": [
      "Assessment",
      "Consultation",
      "Counselling",
      "Hypnosis",
      "Individual and Couple Therapy",
      "Online Counselling / Phone Therapy",
      "Psychotherapy",
      "Rehabilitation",
      "Stress Management",
      "Therapy"
    ],
    "servicesorgcustom": "TREATMENT WITHOUT MEDICINES - OF ALL PSYCHOLOGICAL PROBLEMS",
    "someinfo": "TREATMENT WITHOUT MEDICINES - FOR ALL PROBLEMS RELATED TO MIND - MOOD - BRAIN - EMOTIONS - MEMORY - OVERTHINKING - DEPRESSION & ANXIETY",
    "userimageCloudinary": {
      "asset_id": "c1b71c94c94ec5c323b1148af35caffb",
      "bytes": 3104711,
      "created_at": "2021-03-23T17:54:32Z",
      "etag": "724596d8d85cc486c77b14139056afab",
      "format": "jpg",
      "height": 2149,
      "original_filename": "IMG_20210226_120016",
      "placeholder": false,
      "public_id": "iwyibccsujzdbhz9wlsy",
      "resource_type": "image",
      "secure_url": "https://res.cloudinary.com/dywkbcfp5/image/upload/v1616522072/iwyibccsujzdbhz9wlsy.jpg",
      "signature": "1ea2d4fd7ca58ad199786ee80f2b1eb786f461be",
      "type": "upload",
      "url": "http://res.cloudinary.com/dywkbcfp5/image/upload/v1616522072/iwyibccsujzdbhz9wlsy.jpg",
      "version": 1616522072,
      "version_id": "d5a9bca97ca1d7404553cc1b6db15795",
      "width": 2147
    },
    "userimage": "https://res.cloudinary.com/dywkbcfp5/image/upload/v1616522072/iwyibccsujzdbhz9wlsy.jpg",
    "geopoint": [80.95464609999999, 26.7816463],
    "latitude": "26.7816463",
    "loca": {
      "type": "MultiPoint",
      "coordinates": [[80.95464609999999, 26.7816463]]
    },
    "longitude": "80.95464609999999",
    "searchcity": "Lucknow",
    "searchcountry": "India",
    "searchprovince": "Uttar Pradesh",
    "searchsuburb": "Lucknow",
    "bodyfont": "Lato",
    "customBlogTitle": "Blog",
    "fontcolour": "#FFF",
    "headingfont": "Slabo",
    "hide3": true,
    "publishSite": true,
    "siteurl": "dr-nitnem-singh-sodhi-neuro-psychologist-modern-healing-centre-lucknow-in",
    "splashimage": "https://res.cloudinary.com/dywkbcfp5/image/upload/f_auto/v1542969244/fecevh41fgihtkrnop17.png",
    "boostUser": false,
    "firstAvailabilityEmail": true,
    "firstAvailabilityEmailDate": "2022-04-29T20:00:31.610Z",
    "officeNumber": "+91 9235344444"
  },
  {
    "_id": "KW7StHYN6fLMQdtRe",
    "name": "Navya",
    "surname": "D Mahajan",
    "professionaltitles": ["Licensed Clinical Psychologist"],
    "terms": true,
    "isorganisation": false,
    "logoImage": false,
    "sliderStats": 1660,
    "emailStats": 55,
    "suggestStats": 18,
    "minisiteStats": 689,
    "showNumberStats": 253,
    "emailOnNumberClick": true,
    "hide5": true,
    "hidePhone": false,
    "layout": "one-page",
    "colour": "6",
    "hideSitePhoneNumber": true,
    "isVerified": false,
    "approved": true,
    "hideprofile": false,
    "receiveemails": false,
    "agegroups": [
      "Adolescents",
      "Adults",
      "Children",
      "Couples",
      "Individuals",
      "Parents"
    ],
    "distanceTherapy": true,
    "fees": "Please inquire",
    "gender": ["Female"],
    "languages": ["English", "Hindi/Urdu", "Punjabi"],
    "licenses": [
      {
        "organisation": "RCI",
        "category": "Clinical Psychologist",
        "region": "India",
        "regnumber": "A 70921",
        "degrees": "2026-05-02T00:00:00.000Z"
      }
    ],
    "offices": [
      {
        "title": "Vishal Khand -3 Gomti Nagar",
        "country": "India",
        "address1": "A-3/238 Vishal Khand-3 Gomti Nagar",
        "suburb": "Lucknow",
        "city": "Lucknow",
        "postcode": "226010",
        "province": "Uttar Pradesh",
        "officenumber": "8527840660",
        "officefax": "8527840660"
      }
    ],
    "professionalname": "MPhil",
    "publicprivate": "private",
    "qualifications": [
      {
        "degrees": "MPhil Clinical Psychologist",
        "institution": "Amity Institute of behavioural and allied sciences",
        "yearcompletion": 2019
      }
    ],
    "services": [
      "Assessment (Psychometric)",
      "Employee Wellness Programme",
      "Individual and Couple Therapy",
      "Psychotherapy (CBT)",
      "Relationship Counselling",
      "Therapy (Online)"
    ],
    "someinfo": "She believes in a collaborative approach in order to bring the desired change in life, and focuses on the process of mindful listening and helping the client.",
    "title": "Ms",
    "userimageCloudinary": {
      "asset_id": "aaaa53812d9fedc1ae69a4dfe9cd2046",
      "bytes": 183613,
      "created_at": "2021-03-02T12:11:34Z",
      "etag": "800f287a5af9996f674da7cee9361024",
      "format": "jpg",
      "height": 925,
      "original_extension": "jpeg",
      "original_filename": "5CE3F703-BF41-4DD0-BDBD-CE9BC7FD6396",
      "placeholder": false,
      "public_id": "tvqo7vlrsxvb7f1hruyc",
      "resource_type": "image",
      "secure_url": "https://res.cloudinary.com/dywkbcfp5/image/upload/v1614687094/tvqo7vlrsxvb7f1hruyc.jpg",
      "signature": "d5d0f5306c6db6734b9b28df59b756a26e6f6afd",
      "type": "upload",
      "url": "http://res.cloudinary.com/dywkbcfp5/image/upload/v1614687094/tvqo7vlrsxvb7f1hruyc.jpg",
      "version": 1614687094,
      "version_id": "26765f51b23396c04e91c150669a0c59",
      "width": 925
    },
    "userimage": "https://res.cloudinary.com/dywkbcfp5/image/upload/v1614687094/tvqo7vlrsxvb7f1hruyc.jpg",
    "geopoint": [80.990071, 26.845222],
    "latitude": "26.845222",
    "loca": {
      "type": "MultiPoint",
      "coordinates": [[80.990071, 26.845222]]
    },
    "longitude": "80.990071",
    "searchcity": "Lucknow",
    "searchcountry": "India",
    "searchprovince": "Uttar Pradesh",
    "searchsuburb": "Lucknow",
    "bodyfont": "Lato",
    "customBlogTitle": "Blog",
    "fontcolour": "#FFF",
    "headingfont": "Slabo",
    "hide3": true,
    "publishSite": true,
    "siteurl": "navya-d-mahajan-lucknow-in",
    "splashimage": "https://res.cloudinary.com/dywkbcfp5/image/upload/f_auto/v1478772561/hpfepj2layc7ylxygekx.jpg",
    "showregnumber": false,
    "hide4": false,
    "practiceinfo": "Non-judgmental and open platform for clients to express their thoughts and feelings.",
    "backgroundimage": "0",
    "boostUser": false,
    "firstAvailabilityEmail": true,
    "firstAvailabilityEmailDate": "2022-05-01T12:00:14.336Z",
    "availabilityStatus": null,
    "nextAvailabilityEmailDate": null,
    "officeNumber": "8527840660"
  },
  {
    "_id": "gMEnvTBzYcrf3b77M",
    "name": "Jahnavi",
    "surname": "Agrawal",
    "professionaltitles": ["Psychotherapist"],
    "terms": true,
    "isorganisation": false,
    "logoImage": false,
    "sliderStats": 2677,
    "emailStats": 26,
    "suggestStats": 48,
    "minisiteStats": 664,
    "showNumberStats": 339,
    "emailOnNumberClick": true,
    "hide5": true,
    "hidePhone": false,
    "layout": "one-page",
    "colour": "1",
    "hideSitePhoneNumber": true,
    "isVerified": false,
    "approved": true,
    "hideprofile": false,
    "receiveemails": false,
    "agegroups": [
      "Adolescents",
      "Adults",
      "Children",
      "Communities",
      "Families",
      "Organisations",
      "Parents"
    ],
    "distanceTherapy": true,
    "fees": "Please inquire",
    "gender": ["Female"],
    "languages": ["English", "Hindi/Urdu"],
    "licenses": [
      {
        "organisation": "Counsellor",
        "category": "Psychotherapist"
      }
    ],
    "offices": [
      {
        "title": "1/235, Rashmi khand Shardanagar , Lucknow",
        "country": "India",
        "address1": "1/235 , Rashmi khand Shardanagar, Lucknow",
        "address2": "Near little millennium school",
        "suburb": "Lucknow",
        "city": "Lucknow",
        "postcode": "226002",
        "province": "Uttar Pradesh",
        "officenumber": "9454321493",
        "officefax": "7355087583"
      }
    ],
    "professionalname": "M.Sc ( Counselling Psych)",
    "professionaltitlecustom": "Counsellor",
    "publicprivate": "private",
    "qualifications": [
      {
        "degrees": "M.sc",
        "institution": "Christ",
        "yearcompletion": 2020
      }
    ],
    "scope": [
      "Abuse (Emotional / Physical)",
      "Adjusting to Change/Life Transitions",
      "Anger Management Issues",
      "Body Image",
      "Burnout",
      "Child Stress and Trauma",
      "Eating and Food Issues"
    ],
    "services": ["Awareness", "Counselling", "Psychotherapy"],
    "someinfo": "An enthusiastic young professional exploring through vulnerabilities of human mind and transforming them into traits of social resellience.",
    "title": "Ms",
    "userimageCloudinary": {
      "asset_id": "8f6e58130d5535e3268a0477576dd6fc",
      "bytes": 64463,
      "created_at": "2021-01-10T02:53:03Z",
      "etag": "6f9f16811760c6675b425a61f515aa60",
      "format": "jpg",
      "height": 1152,
      "original_filename": "IMG-20201204-WA0015",
      "placeholder": false,
      "public_id": "yx3af0tipsy8nalat82y",
      "resource_type": "image",
      "secure_url": "https://res.cloudinary.com/dywkbcfp5/image/upload/v1610247183/yx3af0tipsy8nalat82y.jpg",
      "signature": "e496ac918bad7b671c5a6947c5da5b9fa5246599",
      "type": "upload",
      "url": "http://res.cloudinary.com/dywkbcfp5/image/upload/v1610247183/yx3af0tipsy8nalat82y.jpg",
      "version": 1610247183,
      "version_id": "23088d46cb904c934a7d5ec5f55a41d6",
      "width": 604
    },
    "userimage": "https://res.cloudinary.com/dywkbcfp5/image/upload/v1610247183/yx3af0tipsy8nalat82y.jpg",
    "geopoint": [80.9315733, 26.7893651],
    "latitude": "26.7893651",
    "loca": {
      "type": "MultiPoint",
      "coordinates": [[80.9315733, 26.7893651]]
    },
    "longitude": "80.9315733",
    "searchcity": "Lucknow",
    "searchcountry": "India",
    "searchprovince": "Uttar Pradesh",
    "searchsuburb": "Lucknow",
    "bodyfont": "Lato",
    "customBlogTitle": "Blog",
    "fontcolour": "#FFF",
    "headingfont": "Slabo",
    "hide3": true,
    "publishSite": true,
    "siteurl": "jahnavi-agrawal-lucknow-in",
    "splashimage": "https://res.cloudinary.com/dywkbcfp5/image/upload/f_auto/v1542969244/fecevh41fgihtkrnop17.png",
    "seenPhoneNumber": ["DP7vscWfAc3Jk4pcf"],
    "boostUser": false,
    "firstAvailabilityEmail": true,
    "firstAvailabilityEmailDate": "2022-04-30T03:00:14.793Z",
    "officeNumber": "9454321493"
  },
  {
    "_id": "DP7vscWfAc3Jk4pcf",
    "name": "MindLabs",
    "organisationtype": ["Mental Health Clinic"],
    "terms": true,
    "isorganisation": true,
    "logoImage": false,
    "sliderStats": 392,
    "emailStats": 17,
    "suggestStats": 12,
    "minisiteStats": 455,
    "showNumberStats": 198,
    "emailOnNumberClick": true,
    "hide5": true,
    "hidePhone": false,
    "layout": "one-page",
    "colour": "1",
    "hideSitePhoneNumber": true,
    "isVerified": false,
    "approved": true,
    "hideprofile": false,
    "receiveemails": false,
    "agegroups": [
      "All ages",
      "Adolescents",
      "Adults",
      "Children",
      "Couples",
      "Elderly",
      "Families",
      "Individuals",
      "Organisations",
      "Parents"
    ],
    "fees": "Please inquire",
    "languages": ["English", "Hindi/Urdu"],
    "offices": [
      {
        "title": "MindLabs Centre for Mental Health Care",
        "country": "India",
        "address1": "C1B SBI Colony Gayatripuram",
        "address2": "Kursi Road",
        "suburb": "Lucknow",
        "city": "Lucknow",
        "postcode": "226022",
        "province": "Uttar Pradesh",
        "officenumber": "9235691635",
        "officefax": "9807306444"
      }
    ],
    "publicprivate": "private",
    "servicesorg": [
      "Assessment",
      "Assessment (Developmental)",
      "Child and Adolescent Services",
      "Counselling",
      "Counselling (Marriage)",
      "Employee Assistance Programme (EAP)",
      "Individual and Couple Therapy",
      "Psychotherapy",
      "Psychotherapy (CBT)",
      "Relationship Counselling"
    ],
    "servicesorgcustom": "Therapy for OCD, special education, learning disability remedy",
    "someinfo": "Team of Lucknow's best experienced and skilled mental health professions working under one roof.",
    "staff": [
      "Child Psychotherapists",
      "Couples Counsellors",
      "Couples Psychotherapists",
      "Family Therapists",
      "Hypnotherapists",
      "Life Coaches",
      "Occupational Therapists",
      "Psychologists",
      "Psychologists (Clinical)",
      "Psychologists (Counselling)"
    ],
    "userimageCloudinary": {
      "asset_id": "ff7f4c993c930ea53eddc06ba3fc4d30",
      "bytes": 54523,
      "created_at": "2020-12-30T13:42:41Z",
      "etag": "f95be21c452d81e0598f0d235b329bc0",
      "format": "jpg",
      "height": 686,
      "original_filename": "dr-kavita-dhingra-tedhi-pulia-lucknow-psychologist-doctors-1xbzuw3",
      "placeholder": false,
      "public_id": "d2md97poqdilx6jiqlt7",
      "resource_type": "image",
      "secure_url": "https://res.cloudinary.com/dywkbcfp5/image/upload/v1609335761/d2md97poqdilx6jiqlt7.jpg",
      "signature": "8c622dff855fb25e915cd320a5a5b882dab9eea6",
      "type": "upload",
      "url": "http://res.cloudinary.com/dywkbcfp5/image/upload/v1609335761/d2md97poqdilx6jiqlt7.jpg",
      "version": 1609335761,
      "version_id": "026c6ac2695d81b41abb5c7c5e89934a",
      "width": 1024
    },
    "userimage": "https://res.cloudinary.com/dywkbcfp5/image/upload/v1609335761/d2md97poqdilx6jiqlt7.jpg",
    "geopoint": [80.96106309999999, 26.9142315],
    "latitude": "26.9142315",
    "loca": {
      "type": "MultiPoint",
      "coordinates": [[80.96106309999999, 26.9142315]]
    },
    "longitude": "80.96106309999999",
    "searchcity": "Lucknow",
    "searchcountry": "India",
    "searchprovince": "Uttar Pradesh",
    "searchsuburb": "Lucknow",
    "bodyfont": "Lato",
    "customBlogTitle": "Blog",
    "fontcolour": "#FFF",
    "headingfont": "Slabo",
    "hide3": true,
    "publishSite": true,
    "siteurl": "mindlabs-lucknow-in",
    "splashimage": "https://res.cloudinary.com/dywkbcfp5/image/upload/f_auto/v1542969244/fecevh41fgihtkrnop17.png",
    "seenPhoneNumber": ["FZfEQCPCnhbDxXAYD"],
    "boostUser": false,
    "firstAvailabilityEmail": true,
    "firstAvailabilityEmailDate": "2022-04-30T22:00:13.686Z",
    "officeNumber": "9235691635"
  },
  {
    "_id": "FZfEQCPCnhbDxXAYD",
    "name": "Dr Ashutosh Srivastava",
    "organisationtype": ["Mental Health Organisation"],
    "terms": true,
    "isorganisation": true,
    "logoImage": false,
    "sliderStats": 605,
    "emailStats": 10,
    "suggestStats": 25,
    "minisiteStats": 421,
    "showNumberStats": 128,
    "emailOnNumberClick": true,
    "hide5": true,
    "hidePhone": false,
    "layout": "top-nav",
    "colour": "1",
    "hideSitePhoneNumber": true,
    "approved": true,
    "hideprofile": false,
    "receiveemails": false,
    "agegroups": [
      "All ages",
      "Adolescents",
      "Adults",
      "Couples",
      "Individuals",
      "Organisations"
    ],
    "fees": "Direct payment",
    "languages": ["English", "Hindi/Urdu"],
    "licenses": [
      {
        "organisation": "Rehabilitation Council of India",
        "category": "Clinical Psychologist"
      }
    ],
    "offices": [
      {
        "title": "Psyuni",
        "country": "India",
        "address1": "529/228 C Rahim Nagar",
        "address2": "Mahanagar",
        "suburb": "Lucknow",
        "city": "Lucknow",
        "postcode": "226006",
        "province": "Uttar Pradesh",
        "officenumber": "9151909090"
      }
    ],
    "publicprivate": "public",
    "servicesorg": [
      "Assessment (Developmental)",
      "Assessment (Psychometric)",
      "Consultation",
      "Corporate Workshops",
      "Counselling",
      "Counselling (Career)",
      "Counselling (Marriage)",
      "Individual and Couple Therapy",
      "Psychology (Clinical)",
      "Psychology (Counselling)"
    ],
    "servicesorgcustom": "ReAttach Therapy",
    "someinfo": "A Clinical Psychology & Counselling setup for all kind of related services",
    "staff": [
      "Certified Rehabilitation Counsellors",
      "Child Psychotherapists",
      "Couples Counsellors",
      "Dieticians",
      "Licensed Professional Clinical Counsellors",
      "Licensed Psychologists",
      "Psychologists (Clinical)",
      "Therapists/Counsellors Practicing Under Supervision"
    ],
    "userimageCloudinary": {
      "bytes": 5156229,
      "created_at": "2019-09-09T09:37:43Z",
      "etag": "ea0a1c0758dc838ed9e877b3eca5915c",
      "format": "jpg",
      "height": 2500,
      "original_filename": "ReAttach congres 2018-94",
      "placeholder": false,
      "public_id": "d9xj8qbsltbtlyi4w8rm",
      "resource_type": "image",
      "secure_url": "https://res.cloudinary.com/dywkbcfp5/image/upload/v1568021863/d9xj8qbsltbtlyi4w8rm.jpg",
      "signature": "d87be4d702c54bacbec6287637ff73ef0dd2ba0b",
      "type": "upload",
      "url": "http://res.cloudinary.com/dywkbcfp5/image/upload/v1568021863/d9xj8qbsltbtlyi4w8rm.jpg",
      "version": 1568021863,
      "width": 2500
    },
    "userimage": "https://res.cloudinary.com/dywkbcfp5/image/upload/v1568021863/d9xj8qbsltbtlyi4w8rm.jpg",
    "geopoint": [80.9649081, 26.8835689],
    "latitude": "26.8835689",
    "loca": {
      "type": "MultiPoint",
      "coordinates": [[80.9649081, 26.8835689]]
    },
    "longitude": "80.9649081",
    "searchcity": "Lucknow",
    "searchcountry": "India",
    "searchprovince": "Uttar Pradesh",
    "searchsuburb": "Lucknow",
    "bodyfont": "Merriweather",
    "customBlogTitle": "Blog",
    "fontcolour": "#FFF",
    "headingfont": "Varela Round",
    "hide3": true,
    "publishSite": true,
    "siteurl": "drashutoshsrivastava",
    "splashimage": "https://res.cloudinary.com/dywkbcfp5/image/upload/v1538115859/trhphrubyyikojtut5kj.jpg",
    "backgroundimage": "0",
    "showregnumber": false,
    "boostUser": false,
    "firstAvailabilityEmail": true,
    "firstAvailabilityEmailDate": "2022-04-29T21:00:03.836Z",
    "officeNumber": "9151909090"
  }
]
